{
  "users": [
    {
      "name": "zzcxzc",
      "email": "tin@zzz.com",
      "password": "123456",
      "number": "1232133",
      "id": "11"
    },
    {
      "name": "Tin",
      "number": "19921",
      "id": "ku10OUgBv"
    }
  ],
  "products": [
    {
      "id": "9ffac6b1-dd6e-4607-89e3-abd66521313c",
      "name": "Two of a Kind",
      "price": 934,
      "image": "http://lorempixel.com/300/200/"
    },
    {
      "id": "b5234bc4-549d-4413-8b17-5bc84233eef5",
      "name": "Disco Dancer",
      "price": 664,
      "image": "http://lorempixel.com/300/200/cats/"
    },
    {
      "id": "38cae334-daca-4aa0-a194-679467a0a3c4",
      "name": "Farscape: The Peacekeeper Wars",
      "price": 765,
      "image": "http://lorempixel.com/300/200/city/"
    },
    {
      "id": "e7a4504b-3dfc-401f-8d86-c07c2079ecc3",
      "name": "Until Death",
      "price": 469,
      "image": "http://lorempixel.com/300/200/animals/"
    },
    {
      "id": "19bbd1e8-a37d-4af1-b8ee-9de759e6af7f",
      "name": "Teenage Mutant Ninja Turtles",
      "price": 141,
      "image": "http://lorempixel.com/300/200/city/"
    },
    {
      "id": "2fc7c25d-d8ec-46b4-921f-32ff5da0973b",
      "name": "Police, Adjective (Politist, adj.)",
      "price": 663,
      "image": "http://lorempixel.com/300/200/animals/"
    },
    {
      "id": "3109e3aa-d273-4070-bf00-e9e15e0cbe78",
      "name": "Seven Years Bad Luck",
      "price": 549,
      "image": "http://lorempixel.com/300/200/cats/"
    },
    {
      "id": "f595613f-ff37-4d07-a0aa-5a8cea080af1",
      "name": "When Marnie Was There",
      "price": 225,
      "image": "http://lorempixel.com/300/200/cats/"
    },
    {
      "id": "b0dc71b9-b031-41bd-a60b-a4b66494ebab",
      "name": "Kivski Freski",
      "price": 279,
      "image": "http://lorempixel.com/300/200/cats/"
    },
    {
      "id": "af3d1031-808e-46fa-80e8-afe8ae1ad296",
      "name": "Where the Day Takes You",
      "price": 491,
      "image": "http://lorempixel.com/300/200/cats/"
    },
    {
      "id": "c3aa2dee-8a2a-48bb-ac89-06fcaedf9db8",
      "name": "Perfect Man, The",
      "price": 613,
      "image": "http://lorempixel.com/300/200/city/"
    },
    {
      "id": "1139c21d-9607-4ed7-be8f-c697d16c1c3c",
      "name": "Jawbreaker",
      "price": 479,
      "image": "http://lorempixel.com/300/200/"
    },
    {
      "id": "119b75fc-591d-42ae-8fce-4fd82cf94b7b",
      "name": "Lie with Me",
      "price": 872,
      "image": "http://lorempixel.com/300/200/"
    },
    {
      "id": "f5a9bba7-1421-49f0-a554-6b3240e7c36d",
      "name": "Dinotopia: Quest for the Ruby Sunstone",
      "price": 326,
      "image": "http://lorempixel.com/300/200/city/"
    },
    {
      "id": "ba4bec28-3928-4139-b0e6-ac8d3c6f0759",
      "name": "Red Lights (Feux rouges)",
      "price": 64,
      "image": "http://lorempixel.com/300/200/city/"
    },
    {
      "id": "10a33936-32b9-4548-afaf-b00dbbc99b64",
      "name": "Haunting of Molly Hartley, The",
      "price": 530,
      "image": "http://lorempixel.com/300/200/city/"
    },
    {
      "id": "fe14c676-7019-4461-8905-7308c10e282b",
      "name": "Stone Left Unturned, A (Kovat miehet)",
      "price": 905,
      "image": "http://lorempixel.com/300/200/"
    },
    {
      "id": "90aa1475-8f38-4306-9370-22159f57e6e5",
      "name": "Brother's Kiss, A",
      "price": 891,
      "image": "http://lorempixel.com/300/200/cats/"
    },
    {
      "id": "52b5f7ea-ec3c-4dd7-9553-7e62e614f337",
      "name": "Fifty-Fifty (a.k.a. Schizo) (Shiza)",
      "price": 921,
      "image": "http://lorempixel.com/300/200/animals/"
    },
    {
      "id": "8d9faae2-e672-44ad-9d6c-f73a85928795",
      "name": "Naked Jungle, The",
      "price": 118,
      "image": "http://lorempixel.com/300/200/city/"
    },
    {
      "id": "493ea253-7896-4eef-bd0e-8d26ec0da224",
      "name": "Debtocracy",
      "price": 808,
      "image": "http://lorempixel.com/300/200/animals/"
    },
    {
      "id": "cf78af2b-194d-45cc-9290-667393d420bf",
      "name": "Great Gatsby, The",
      "price": 341,
      "image": "http://lorempixel.com/300/200/cats/"
    },
    {
      "id": "fdf3c926-bdd0-4318-b5e5-977ccf9b440b",
      "name": "That Certain Woman",
      "price": 952,
      "image": "http://lorempixel.com/300/200/cats/"
    },
    {
      "id": "05995b6e-4d59-4d25-bec1-ca693d283860",
      "name": "Quiet American, The",
      "price": 131,
      "image": "http://lorempixel.com/300/200/city/"
    },
    {
      "id": "08c16d4d-1d33-46a4-8b38-4b5c97ae5b61",
      "name": "Story of the Weeping Camel, The (Geschichte vom weinenden Kamel, Die)",
      "price": 104,
      "image": "http://lorempixel.com/300/200/"
    },
    {
      "id": "cfc5b9fe-e90a-4712-a080-0f341267e278",
      "name": "Dark Angel: Ascent, The",
      "price": 787,
      "image": "http://lorempixel.com/300/200/"
    },
    {
      "id": "9e70bb84-ffb0-4a17-a4dd-af24433e6f4b",
      "name": "Neds",
      "price": 265,
      "image": "http://lorempixel.com/300/200/animals/"
    },
    {
      "id": "608cf883-4699-425c-841c-6c56399e09cc",
      "name": "Gunfight at Dodge City, The",
      "price": 580,
      "image": "http://lorempixel.com/300/200/city/"
    },
    {
      "id": "11dba681-2e24-41dd-a2ac-62c2f4dacd6d",
      "name": "Joneses, The",
      "price": 61,
      "image": "http://lorempixel.com/300/200/animals/"
    },
    {
      "id": "56e1599b-044c-4542-b586-28b071057d7a",
      "name": "Day of the Dolphin, The",
      "price": 835,
      "image": "http://lorempixel.com/300/200/cats/"
    },
    {
      "id": "7b16e40c-f65d-4bfb-9e44-3400c3b9a394",
      "name": "My Wife, A Body to Love",
      "price": 990,
      "image": "http://lorempixel.com/300/200/"
    },
    {
      "id": "e10b79ce-9757-49e9-850c-b720c1ba9add",
      "name": "Nightmaster (Watch the Shadows Dance)",
      "price": 558,
      "image": "http://lorempixel.com/300/200/city/"
    },
    {
      "id": "347f8ae6-0d9f-440e-9530-45da8c72478d",
      "name": "Watermarks",
      "price": 938,
      "image": "http://lorempixel.com/300/200/cats/"
    },
    {
      "id": "ab5c6861-b0e7-42dc-9687-79d615d3e450",
      "name": "After the Rehearsal (Efter repetitionen)",
      "price": 288,
      "image": "http://lorempixel.com/300/200/city/"
    },
    {
      "id": "8028240c-6cab-423e-a993-89797024dc8a",
      "name": "Swept Away (Travolti da un insolito destino nell'azzurro mare d'Agosto)",
      "price": 670,
      "image": "http://lorempixel.com/300/200/"
    },
    {
      "id": "f33ce8a7-1022-43c2-8f7e-e82a3e79bde9",
      "name": "Puppet Master: Axis of Evil (Puppet Master 10)",
      "price": 552,
      "image": "http://lorempixel.com/300/200/cats/"
    },
    {
      "id": "37c05412-cb91-4d30-9615-ff0bfc9a2564",
      "name": "Possession of David O'Reilly, The ",
      "price": 108,
      "image": "http://lorempixel.com/300/200/animals/"
    },
    {
      "id": "2804eb08-cd5b-4a2e-851d-a1da8ccbdca0",
      "name": "And Now a Word from Our Sponsor",
      "price": 561,
      "image": "http://lorempixel.com/300/200/city/"
    },
    {
      "id": "d20cca7a-35d9-4434-b45c-73a183d2666c",
      "name": "Be with Me",
      "price": 313,
      "image": "http://lorempixel.com/300/200/"
    },
    {
      "id": "e0d10b8f-8a5c-4d62-be50-c02d84c9ace7",
      "name": "Substance: Albert Hofmann's LSD, The",
      "price": 868,
      "image": "http://lorempixel.com/300/200/"
    },
    {
      "id": "9bd1f041-090e-4676-8fc1-c5d1fb64fa84",
      "name": "Killing Room, The",
      "price": 943,
      "image": "http://lorempixel.com/300/200/animals/"
    },
    {
      "id": "77dd1ce9-14ab-4f86-b925-a70077fc35d6",
      "name": "Wild, Wild Planet (I criminali della galassia)",
      "price": 511,
      "image": "http://lorempixel.com/300/200/"
    },
    {
      "id": "eb56f2de-1d7d-4b96-a7f1-9f8a079b2931",
      "name": "Paradise",
      "price": 120,
      "image": "http://lorempixel.com/300/200/cats/"
    },
    {
      "id": "937cf141-6cbe-4915-b3f5-2bc29743dab0",
      "name": "Living with the Fosters",
      "price": 646,
      "image": "http://lorempixel.com/300/200/cats/"
    },
    {
      "id": "59b0e883-f02a-4695-a5a4-928091667072",
      "name": "Klimt",
      "price": 593,
      "image": "http://lorempixel.com/300/200/cats/"
    },
    {
      "id": "2dc39a22-c86a-4057-8de4-9ff87cffa5c6",
      "name": "Real Blonde, The",
      "price": 617,
      "image": "http://lorempixel.com/300/200/"
    },
    {
      "id": "2329037a-678d-4120-b088-c7752399e3c5",
      "name": "Police Academy 5: Assignment: Miami Beach",
      "price": 233,
      "image": "http://lorempixel.com/300/200/cats/"
    },
    {
      "id": "c9a4e0fd-505b-4f78-87eb-08dc8d9b621e",
      "name": "3000 Miles to Graceland",
      "price": 152,
      "image": "http://lorempixel.com/300/200/cats/"
    },
    {
      "id": "ab619c2c-af10-4e8f-ad57-6ca3ad9e69a7",
      "name": "Most Wanted Man, A",
      "price": 259,
      "image": "http://lorempixel.com/300/200/cats/"
    },
    {
      "id": "8c7d3e38-d4f5-4952-87d0-98a6f2b2ccb5",
      "name": "Maniac Cop 2",
      "price": 354,
      "image": "http://lorempixel.com/300/200/"
    },
    {
      "id": "1764589a-93a7-478d-87b8-85a5d1fc2a4a",
      "name": "Divide, The",
      "price": 591,
      "image": "http://lorempixel.com/300/200/"
    },
    {
      "id": "35bae32d-9aa9-4282-b277-a87a656c293c",
      "name": "Two Mrs. Carrolls, The",
      "price": 280,
      "image": "http://lorempixel.com/300/200/city/"
    },
    {
      "id": "81c090fd-2601-406e-bbc2-62f1d0dc3df2",
      "name": "Baby Face",
      "price": 589,
      "image": "http://lorempixel.com/300/200/city/"
    },
    {
      "id": "dfbd2117-4be1-4884-a117-ea8b62c6479c",
      "name": "Lilies of the Field",
      "price": 737,
      "image": "http://lorempixel.com/300/200/cats/"
    },
    {
      "id": "6a83d0be-d501-4e31-a866-66bbc6589d53",
      "name": "General, The",
      "price": 535,
      "image": "http://lorempixel.com/300/200/cats/"
    },
    {
      "id": "052de3ec-c67b-4286-a4b0-8f874fea0f90",
      "name": "Godzilla vs. Destroyah (Gojira vs. Desutoroiâ) ",
      "price": 504,
      "image": "http://lorempixel.com/300/200/animals/"
    },
    {
      "id": "34f12b51-c345-4b0d-b740-540af142fd34",
      "name": "Silence, The (Das letzte Schweigen)",
      "price": 568,
      "image": "http://lorempixel.com/300/200/"
    },
    {
      "id": "65d0aa6e-b7cd-48e9-be52-cee22f96d43d",
      "name": "7 Plus Seven",
      "price": 843,
      "image": "http://lorempixel.com/300/200/cats/"
    },
    {
      "id": "66efc23a-8ae3-4604-aae6-2db66bb93e53",
      "name": "Death on the Nile",
      "price": 111,
      "image": "http://lorempixel.com/300/200/animals/"
    },
    {
      "id": "86d8161a-b276-416b-918b-5a3b1dc9e40d",
      "name": "Harry Potter and the Deathly Hallows: Part 2",
      "price": 125,
      "image": "http://lorempixel.com/300/200/"
    },
    {
      "id": "3c0fa6a7-ff1b-4151-bf3d-dfe3c4f99769",
      "name": "Last Letter, The (La dernière lettre)",
      "price": 56,
      "image": "http://lorempixel.com/300/200/city/"
    },
    {
      "id": "3ad9a87c-51f6-4379-96d6-04c9c1ac812f",
      "name": "Elephant",
      "price": 301,
      "image": "http://lorempixel.com/300/200/cats/"
    },
    {
      "id": "1c078f04-3caf-407a-a610-d5173f061a59",
      "name": "Some Folks Call It a Sling Blade",
      "price": 96,
      "image": "http://lorempixel.com/300/200/cats/"
    },
    {
      "id": "72615bd0-477b-4634-b9d1-bf81ec26caf1",
      "name": "Illusionist, The",
      "price": 95,
      "image": "http://lorempixel.com/300/200/"
    },
    {
      "id": "7258e80a-23ee-43e2-a537-ee2b6ac27351",
      "name": "God's Country",
      "price": 378,
      "image": "http://lorempixel.com/300/200/animals/"
    },
    {
      "id": "5e60af8b-4448-4d7e-9324-0908aeb61e87",
      "name": "Titus",
      "price": 376,
      "image": "http://lorempixel.com/300/200/animals/"
    },
    {
      "id": "ac7ec415-6093-47ca-9171-aba3df7c95cf",
      "name": "Time to Kill, A",
      "price": 432,
      "image": "http://lorempixel.com/300/200/"
    },
    {
      "id": "1446a7e5-c0b4-4149-9a4e-5296196632d6",
      "name": "Tumbledown",
      "price": 691,
      "image": "http://lorempixel.com/300/200/cats/"
    },
    {
      "id": "11c79aa4-2a58-4599-9815-bf330d671ee1",
      "name": "Red Beard (Akahige)",
      "price": 604,
      "image": "http://lorempixel.com/300/200/animals/"
    },
    {
      "id": "04144872-441c-4577-b1fb-a2919dd2cc15",
      "name": "Pudana Last of the Line (Sukunsa viimeinen)",
      "price": 229,
      "image": "http://lorempixel.com/300/200/city/"
    },
    {
      "id": "9efc60c8-23d6-4f60-addb-c00efd2cb577",
      "name": "Affair of Love, An (Liaison pornographique, Une)",
      "price": 890,
      "image": "http://lorempixel.com/300/200/cats/"
    },
    {
      "id": "97f589f0-8c45-48fe-9026-40d184ba0732",
      "name": "A Christmas Kiss",
      "price": 534,
      "image": "http://lorempixel.com/300/200/animals/"
    },
    {
      "id": "c0448350-ed5a-48f3-877a-57610d35f2ff",
      "name": "Eye of the Tiger",
      "price": 362,
      "image": "http://lorempixel.com/300/200/animals/"
    },
    {
      "id": "a2d464c5-df6b-4349-a607-5c1cbe6c095d",
      "name": "Final Conflict, The (a.k.a. Omen III: The Final Conflict)",
      "price": 421,
      "image": "http://lorempixel.com/300/200/"
    },
    {
      "id": "24576aab-2df5-436c-9e57-6f5aad3611bf",
      "name": "Motivational Growth",
      "price": 825,
      "image": "http://lorempixel.com/300/200/animals/"
    },
    {
      "id": "fa53bb7f-b164-4929-8655-468e5a047036",
      "name": "Pyaar Ka Punchnama",
      "price": 571,
      "image": "http://lorempixel.com/300/200/"
    },
    {
      "id": "ff613966-1b3e-4910-8ebb-33b10ac37d10",
      "name": "Young and the Damned, The (Olvidados, Los)",
      "price": 832,
      "image": "http://lorempixel.com/300/200/"
    },
    {
      "id": "726c1fb2-f954-4386-8193-683e7a93f69f",
      "name": "Frankenweenie",
      "price": 780,
      "image": "http://lorempixel.com/300/200/cats/"
    },
    {
      "id": "ea5f353b-706a-4f9d-b599-e02c06453abd",
      "name": "Chasing Ice",
      "price": 450,
      "image": "http://lorempixel.com/300/200/"
    },
    {
      "id": "d0976081-f544-4502-9b8e-8c9bfac787bb",
      "name": "Chalte Chalte",
      "price": 958,
      "image": "http://lorempixel.com/300/200/city/"
    },
    {
      "id": "1f241f52-1255-44ba-a762-ca8f1b423c72",
      "name": "Chasing Christmas",
      "price": 803,
      "image": "http://lorempixel.com/300/200/city/"
    },
    {
      "id": "5dd477c1-c9c5-4a4d-84c3-8db49d1a0d02",
      "name": "Fast, Cheap & Out of Control",
      "price": 335,
      "image": "http://lorempixel.com/300/200/city/"
    },
    {
      "id": "9d71b1bf-dd81-41a9-9394-8654df361881",
      "name": "Star 80",
      "price": 227,
      "image": "http://lorempixel.com/300/200/cats/"
    },
    {
      "id": "c7dc218d-3f12-409c-9e94-4c209065b57b",
      "name": "Buud Yam",
      "price": 606,
      "image": "http://lorempixel.com/300/200/"
    },
    {
      "id": "a867319f-c82e-40c7-837e-661bd778a85d",
      "name": "Winged Migration (Peuple migrateur, Le)",
      "price": 344,
      "image": "http://lorempixel.com/300/200/cats/"
    },
    {
      "id": "ae85e17b-1a45-4732-b687-aa34f3fbec38",
      "name": "Shattered Glass",
      "price": 854,
      "image": "http://lorempixel.com/300/200/"
    },
    {
      "id": "02b83cb4-e77d-4984-b08a-135ae626cc1c",
      "name": "Blind Dating",
      "price": 873,
      "image": "http://lorempixel.com/300/200/"
    },
    {
      "id": "80ede89a-5570-4261-9246-ec475b69ca70",
      "name": "Love Sick (Legaturi bolnavicioase)",
      "price": 1000,
      "image": "http://lorempixel.com/300/200/animals/"
    },
    {
      "id": "538f2034-b6a8-475b-ae3e-21d3ab7dd7e4",
      "name": "Party Monster",
      "price": 824,
      "image": "http://lorempixel.com/300/200/"
    },
    {
      "id": "e646fab0-60ae-48d5-ad04-970b789aad17",
      "name": "Broadway",
      "price": 914,
      "image": "http://lorempixel.com/300/200/cats/"
    },
    {
      "id": "72ce61e0-1881-45e4-912f-1f79592bc22a",
      "name": "Inbetweeners 2, The",
      "price": 863,
      "image": "http://lorempixel.com/300/200/"
    },
    {
      "id": "aaf13a43-4971-4176-82a8-2d367a909500",
      "name": "Slither",
      "price": 209,
      "image": "http://lorempixel.com/300/200/city/"
    },
    {
      "id": "763ce0bf-b319-4df1-8180-89d0b87e104a",
      "name": "Idle Class, The",
      "price": 850,
      "image": "http://lorempixel.com/300/200/"
    },
    {
      "id": "a2bc237e-b9a9-47da-a38e-dab3b101d656",
      "name": "Winter Solstice",
      "price": 37,
      "image": "http://lorempixel.com/300/200/"
    },
    {
      "id": "329f49f4-5f9b-4451-a904-9ddba15d796e",
      "name": "Teenage Mutant Ninja Turtles",
      "price": 255,
      "image": "http://lorempixel.com/300/200/"
    },
    {
      "id": "a12e5d11-b394-427b-a5cb-946c7d8acfd1",
      "name": "Police",
      "price": 448,
      "image": "http://lorempixel.com/300/200/animals/"
    },
    {
      "id": "15dda5a4-bdf2-4383-ba45-a48a4aa5033a",
      "name": "The Sea That Thinks",
      "price": 1000,
      "image": "http://lorempixel.com/300/200/city/"
    },
    {
      "id": "57220429-9f80-4f39-b9ea-360694161e9f",
      "name": "Game 6",
      "price": 287,
      "image": "http://lorempixel.com/300/200/"
    },
    {
      "id": "29fae4b1-1a6e-412d-acfa-dfce180e99fb",
      "name": "It's Complicated",
      "price": 372,
      "image": "http://lorempixel.com/300/200/cats/"
    },
    {
      "id": "5ae5a4b1-7cfa-4f28-9e58-cb1c962c4822",
      "name": "More Dead Than Alive",
      "price": 158,
      "image": "http://lorempixel.com/300/200/city/"
    }
  ]
}
